demian_parts/__init__.py
demian_parts/admin.py
demian_parts/apps.py
demian_parts/models.py
demian_parts/views.py
demian_parts/static/calendar-19/css/bootstrap.min.css
demian_parts/static/calendar-19/css/bootstrap.min.css.map
demian_parts/static/calendar-19/css/owl.carousel.min.css
demian_parts/static/calendar-19/css/style.css
demian_parts/static/calendar-19/css/bootstrap/mixins/_buttons.css
demian_parts/static/calendar-19/css/bootstrap/mixins/_grid.css
demian_parts/static/calendar-19/css/bootstrap/mixins/_resize.css
demian_parts/static/calendar-19/fonts/icomoon/Read Me.txt
demian_parts/static/calendar-19/fonts/icomoon/demo.html
demian_parts/static/calendar-19/fonts/icomoon/selection.json
demian_parts/static/calendar-19/fonts/icomoon/style.css
demian_parts/static/calendar-19/fonts/icomoon/demo-files/demo.css
demian_parts/static/calendar-19/fonts/icomoon/demo-files/demo.js
demian_parts/static/calendar-19/fonts/icomoon/fonts/icomoon.eot
demian_parts/static/calendar-19/fonts/icomoon/fonts/icomoon.svg
demian_parts/static/calendar-19/fonts/icomoon/fonts/icomoon.ttf
demian_parts/static/calendar-19/fonts/icomoon/fonts/icomoon.woff
demian_parts/static/calendar-19/fullcalendar/packages/bootstrap/LICENSE.txt
demian_parts/static/calendar-19/fullcalendar/packages/bootstrap/README.md
demian_parts/static/calendar-19/fullcalendar/packages/bootstrap/main.css
demian_parts/static/calendar-19/fullcalendar/packages/bootstrap/main.d.ts
demian_parts/static/calendar-19/fullcalendar/packages/bootstrap/main.esm.js
demian_parts/static/calendar-19/fullcalendar/packages/bootstrap/main.js
demian_parts/static/calendar-19/fullcalendar/packages/bootstrap/main.min.css
demian_parts/static/calendar-19/fullcalendar/packages/bootstrap/main.min.js
demian_parts/static/calendar-19/fullcalendar/packages/bootstrap/package.json
demian_parts/static/calendar-19/fullcalendar/packages/core/LICENSE.txt
demian_parts/static/calendar-19/fullcalendar/packages/core/README.md
django_demian_parts-0.6.0.dist-info/LICENSE
django_demian_parts-0.6.0.dist-info/METADATA
django_demian_parts-0.6.0.dist-info/WHEEL
django_demian_parts-0.6.0.dist-info/top_level.txt
django_demian_parts-0.6.0.dist-info/RECORD
