Metadata-Version: 2.1
Name: django-demian_parts
Version: 0.6.0
Summary: parts for demiansoft
Home-page: https://www.demiansoft.com
Author: hyungjin kim
Author-email: hj3415@gmail.com
Project-URL: Bug Tracker, https://pypi.org/project/django-demian_parts/
Classifier: License :: OSI Approved :: BSD License
Classifier: Operating System :: OS Independent
Classifier: Programming Language :: Python :: 3
Requires-Python: >=3.8
License-File: LICENSE
Requires-Dist: Django >=4.0.6
Requires-Dist: Pillow >=9.2.0
